{"_format":"","paths":{"artifacts":"out","build_infos":"out/build-info","sources":"src","tests":"test","scripts":"script","libraries":["node_modules"]},"files":{"contracts/CopyTradeRouter.sol":{"lastModificationDate":1782852231511,"contentHash":"b3c551af8fb131a1","interfaceReprHash":null,"sourceName":"contracts/CopyTradeRouter.sol","imports":[],"versionRequirement":"^0.8.20","artifacts":{"CopyTradeRouter":{"0.8.26":{"default":{"path":"CopyTradeRouter.sol/CopyTradeRouter.json","build_id":"10b76fb4c5da619e"}}},"IERC20":{"0.8.26":{"default":{"path":"CopyTradeRouter.sol/IERC20.json","build_id":"10b76fb4c5da619e"}}},"ISwapRouterV3":{"0.8.26":{"default":{"path":"CopyTradeRouter.sol/ISwapRouterV3.json","build_id":"10b76fb4c5da619e"}}},"IUniswapV2Router":{"0.8.26":{"default":{"path":"CopyTradeRouter.sol/IUniswapV2Router.json","build_id":"10b76fb4c5da619e"}}},"IWETH":{"0.8.26":{"default":{"path":"CopyTradeRouter.sol/IWETH.json","build_id":"10b76fb4c5da619e"}}}},"seenByCompiler":true},"contracts/SmartAccount.sol":{"lastModificationDate":1782850870882,"contentHash":"5b6f1e08bc212cc3","interfaceReprHash":null,"sourceName":"contracts/SmartAccount.sol","imports":[],"versionRequirement":"^0.8.20","artifacts":{"SmartAccount":{"0.8.26":{"default":{"path":"SmartAccount.sol/SmartAccount.json","build_id":"cff9974d45d01630"}}}},"seenByCompiler":true},"contracts/SmartAccountFactory.sol":{"lastModificationDate":1782850875036,"contentHash":"27d45357b1428c38","interfaceReprHash":null,"sourceName":"contracts/SmartAccountFactory.sol","imports":["contracts/SmartAccount.sol"],"versionRequirement":"^0.8.20","artifacts":{"SmartAccountFactory":{"0.8.26":{"default":{"path":"SmartAccountFactory.sol/SmartAccountFactory.json","build_id":"cff9974d45d01630"}}}},"seenByCompiler":true}},"builds":["10b76fb4c5da619e","cff9974d45d01630"],"profiles":{"default":{"solc":{"optimizer":{"enabled":false,"runs":200},"metadata":{"useLiteralContent":false,"bytecodeHash":"ipfs","appendCBOR":true},"outputSelection":{"*":{"*":["abi","evm.bytecode.object","evm.bytecode.sourceMap","evm.bytecode.linkReferences","evm.deployedBytecode.object","evm.deployedBytecode.sourceMap","evm.deployedBytecode.linkReferences","evm.deployedBytecode.immutableReferences","evm.methodIdentifiers","metadata"]}},"evmVersion":"prague","viaIR":false,"libraries":{}},"vyper":{"evmVersion":"prague","outputSelection":{"*":{"*":["abi","evm.bytecode","evm.deployedBytecode"]}}}}},"preprocessed":false,"mocks":[]}